{"session_id":"1648329012122","state":"screen2","original_query":"?version=v2","user_agent":"Mozilla/5.0 (Linux; Android 9; moto e6 (XT2005DL)) AppleWebKit/537.36 (KHTML, like Gecko) Chrome/98.0.4758.101 Mobile Safari/537.36","platform":"Linux armv7l","task_idx":"17","task_id":"task14","style_id":"spacing15","table_idx":"9","scroll_log":[{"offsetLeft":0,"offsetTop":0,"pageLeft":0,"pageTop":9,"width":360,"height":648,"scale":1,"time":855},{"offsetLeft":0,"offsetTop":0,"pageLeft":0,"pageTop":25.5,"width":360,"height":648,"scale":1,"time":865},{"offsetLeft":0,"offsetTop":0,"pageLeft":0,"pageTop":43,"width":360,"height":648,"scale":1,"time":883},{"offsetLeft":0,"offsetTop":0,"pageLeft":0,"pageTop":61.5,"width":360,"height":648,"scale":1,"time":900},{"offsetLeft":0,"offsetTop":0,"pageLeft":0,"pageTop":78,"width":360,"height":648,"scale":1,"time":917},{"offsetLeft":0,"offsetTop":0,"pageLeft":0,"pageTop":96.5,"width":360,"height":648,"scale":1,"time":933},{"offsetLeft":0,"offsetTop":0,"pageLeft":0,"pageTop":111,"width":360,"height":648,"scale":1,"time":948},{"offsetLeft":0,"offsetTop":0,"pageLeft":0,"pageTop":125.5,"width":360,"height":648,"scale":1,"time":968},{"offsetLeft":0,"offsetTop":0,"pageLeft":0,"pageTop":141,"width":360,"height":648,"scale":1,"time":985},{"offsetLeft":0,"offsetTop":0,"pageLeft":0,"pageTop":158,"width":360,"height":648,"scale":1,"time":1000},{"offsetLeft":0,"offsetTop":0,"pageLeft":0,"pageTop":174.5,"width":360,"height":648,"scale":1,"time":1021},{"offsetLeft":0,"offsetTop":0,"pageLeft":0,"pageTop":188.5,"width":360,"height":648,"scale":1,"time":1053},{"offsetLeft":0,"offsetTop":0,"pageLeft":0,"pageTop":202,"width":360,"height":648,"scale":1,"time":1068},{"offsetLeft":0,"offsetTop":0,"pageLeft":0,"pageTop":214.5,"width":360,"height":648,"scale":1,"time":1085},{"offsetLeft":0,"offsetTop":0,"pageLeft":0,"pageTop":226,"width":360,"height":648,"scale":1,"time":1103},{"offsetLeft":0,"offsetTop":0,"pageLeft":0,"pageTop":236.5,"width":360,"height":648,"scale":1,"time":1119},{"offsetLeft":0,"offsetTop":0,"pageLeft":0,"pageTop":246,"width":360,"height":648,"scale":1,"time":1136},{"offsetLeft":0,"offsetTop":0,"pageLeft":0,"pageTop":254.5,"width":360,"height":648,"scale":1,"time":1151},{"offsetLeft":0,"offsetTop":0,"pageLeft":0,"pageTop":262,"width":360,"height":648,"scale":1,"time":1168},{"offsetLeft":0,"offsetTop":0,"pageLeft":0,"pageTop":268.5,"width":360,"height":648,"scale":1,"time":1185},{"offsetLeft":0,"offsetTop":0,"pageLeft":0,"pageTop":274.5,"width":360,"height":648,"scale":1,"time":1202},{"offsetLeft":0,"offsetTop":0,"pageLeft":0,"pageTop":280,"width":360,"height":648,"scale":1,"time":1220},{"offsetLeft":0,"offsetTop":0,"pageLeft":0,"pageTop":285,"width":360,"height":648,"scale":1,"time":1234},{"offsetLeft":0,"offsetTop":0,"pageLeft":0,"pageTop":289.5,"width":360,"height":648,"scale":1,"time":1253},{"offsetLeft":0,"offsetTop":0,"pageLeft":0,"pageTop":293,"width":360,"height":648,"scale":1,"time":1269},{"offsetLeft":0,"offsetTop":0,"pageLeft":0,"pageTop":296.5,"width":360,"height":648,"scale":1,"time":1287},{"offsetLeft":0,"offsetTop":0,"pageLeft":0,"pageTop":299.5,"width":360,"height":648,"scale":1,"time":1303},{"offsetLeft":0,"offsetTop":0,"pageLeft":0,"pageTop":302.5,"width":360,"height":648,"scale":1,"time":1322},{"offsetLeft":0,"offsetTop":0,"pageLeft":0,"pageTop":305,"width":360,"height":648,"scale":1,"time":1335},{"offsetLeft":0,"offsetTop":0,"pageLeft":0,"pageTop":314.5,"width":360,"height":648,"scale":1,"time":1369},{"offsetLeft":0,"offsetTop":0,"pageLeft":0,"pageTop":335,"width":360,"height":648,"scale":1,"time":1388},{"offsetLeft":0,"offsetTop":0,"pageLeft":0,"pageTop":359.5,"width":360,"height":648,"scale":1,"time":1404},{"offsetLeft":0,"offsetTop":0,"pageLeft":0,"pageTop":386,"width":360,"height":648,"scale":1,"time":1418},{"offsetLeft":0,"offsetTop":0,"pageLeft":0,"pageTop":413.5,"width":360,"height":648,"scale":1,"time":1433},{"offsetLeft":0,"offsetTop":0,"pageLeft":0,"pageTop":442.5,"width":360,"height":648,"scale":1,"time":1449},{"offsetLeft":0,"offsetTop":0,"pageLeft":0,"pageTop":468.5,"width":360,"height":648,"scale":1,"time":1467},{"offsetLeft":0,"offsetTop":0,"pageLeft":0,"pageTop":491,"width":360,"height":648,"scale":1,"time":1484},{"offsetLeft":0,"offsetTop":0,"pageLeft":0,"pageTop":506,"width":360,"height":648,"scale":1,"time":1499},{"offsetLeft":0,"offsetTop":0,"pageLeft":0,"pageTop":534.5,"width":360,"height":648,"scale":1,"time":1516},{"offsetLeft":0,"offsetTop":0,"pageLeft":0,"pageTop":550,"width":360,"height":648,"scale":1,"time":1533},{"offsetLeft":0,"offsetTop":0,"pageLeft":0,"pageTop":573,"width":360,"height":648,"scale":1,"time":1548},{"offsetLeft":0,"offsetTop":0,"pageLeft":0,"pageTop":594.5,"width":360,"height":648,"scale":1,"time":1567},{"offsetLeft":0,"offsetTop":0,"pageLeft":0,"pageTop":615.5,"width":360,"height":648,"scale":1,"time":1582},{"offsetLeft":0,"offsetTop":0,"pageLeft":0,"pageTop":635.5,"width":360,"height":648,"scale":1,"time":1601},{"offsetLeft":0,"offsetTop":0,"pageLeft":0,"pageTop":654,"width":360,"height":648,"scale":1,"time":1617},{"offsetLeft":0,"offsetTop":0,"pageLeft":0,"pageTop":671.5,"width":360,"height":648,"scale":1,"time":1633},{"offsetLeft":0,"offsetTop":0,"pageLeft":0,"pageTop":687.5,"width":360,"height":648,"scale":1,"time":1651},{"offsetLeft":0,"offsetTop":0,"pageLeft":0,"pageTop":702.5,"width":360,"height":648,"scale":1,"time":1667},{"offsetLeft":0,"offsetTop":0,"pageLeft":0,"pageTop":716.5,"width":360,"height":648,"scale":1,"time":1683},{"offsetLeft":0,"offsetTop":0,"pageLeft":0,"pageTop":729.5,"width":360,"height":648,"scale":1,"time":1699},{"offsetLeft":0,"offsetTop":0,"pageLeft":0,"pageTop":741,"width":360,"height":648,"scale":1,"time":1718},{"offsetLeft":0,"offsetTop":0,"pageLeft":0,"pageTop":752.5,"width":360,"height":648,"scale":1,"time":1735},{"offsetLeft":0,"offsetTop":0,"pageLeft":0,"pageTop":762.5,"width":360,"height":648,"scale":1,"time":1749},{"offsetLeft":0,"offsetTop":0,"pageLeft":0,"pageTop":772,"width":360,"height":648,"scale":1,"time":1766},{"offsetLeft":0,"offsetTop":0,"pageLeft":0,"pageTop":781,"width":360,"height":648,"scale":1,"time":1782},{"offsetLeft":0,"offsetTop":0,"pageLeft":0,"pageTop":789,"width":360,"height":648,"scale":1,"time":1798},{"offsetLeft":0,"offsetTop":0,"pageLeft":0,"pageTop":796.5,"width":360,"height":648,"scale":1,"time":1815},{"offsetLeft":0,"offsetTop":0,"pageLeft":0,"pageTop":803.5,"width":360,"height":648,"scale":1,"time":1840},{"offsetLeft":0,"offsetTop":0,"pageLeft":0,"pageTop":817,"width":360,"height":648,"scale":1,"time":1873},{"offsetLeft":0,"offsetTop":0,"pageLeft":0,"pageTop":856,"width":360,"height":648,"scale":1,"time":1884},{"offsetLeft":0,"offsetTop":0,"pageLeft":0,"pageTop":889,"width":360,"height":648,"scale":1,"time":1903},{"offsetLeft":0,"offsetTop":0,"pageLeft":0,"pageTop":931,"width":360,"height":648,"scale":1,"time":1920},{"offsetLeft":0,"offsetTop":0,"pageLeft":0,"pageTop":973.5,"width":360,"height":648,"scale":1,"time":1934},{"offsetLeft":0,"offsetTop":0,"pageLeft":0,"pageTop":1057,"width":360,"height":648,"scale":1,"time":1953},{"offsetLeft":0,"offsetTop":0,"pageLeft":0,"pageTop":1127,"width":360,"height":648,"scale":1,"time":1986},{"offsetLeft":0,"offsetTop":0,"pageLeft":0,"pageTop":1197.5,"width":360,"height":648,"scale":1,"time":2007},{"offsetLeft":0,"offsetTop":0,"pageLeft":0,"pageTop":1267,"width":360,"height":648,"scale":1,"time":2019},{"offsetLeft":0,"offsetTop":0,"pageLeft":0,"pageTop":1336,"width":360,"height":648,"scale":1,"time":2038},{"offsetLeft":0,"offsetTop":0,"pageLeft":0,"pageTop":1403.5,"width":360,"height":648,"scale":1,"time":2052},{"offsetLeft":0,"offsetTop":0,"pageLeft":0,"pageTop":1470.5,"width":360,"height":648,"scale":1,"time":2072},{"offsetLeft":0,"offsetTop":0,"pageLeft":0,"pageTop":1536,"width":360,"height":648,"scale":1,"time":2085},{"offsetLeft":0,"offsetTop":0,"pageLeft":0,"pageTop":1600,"width":360,"height":648,"scale":1,"time":2102},{"offsetLeft":0,"offsetTop":0,"pageLeft":0,"pageTop":1663,"width":360,"height":648,"scale":1,"time":2119},{"offsetLeft":0,"offsetTop":0,"pageLeft":0,"pageTop":1724,"width":360,"height":648,"scale":1,"time":2134},{"offsetLeft":0,"offsetTop":0,"pageLeft":0,"pageTop":1784,"width":360,"height":648,"scale":1,"time":2153},{"offsetLeft":0,"offsetTop":0,"pageLeft":0,"pageTop":1842,"width":360,"height":648,"scale":1,"time":2170},{"offsetLeft":0,"offsetTop":0,"pageLeft":0,"pageTop":1898.5,"width":360,"height":648,"scale":1,"time":2185},{"offsetLeft":0,"offsetTop":0,"pageLeft":0,"pageTop":1953.5,"width":360,"height":648,"scale":1,"time":2203},{"offsetLeft":0,"offsetTop":0,"pageLeft":0,"pageTop":2006.5,"width":360,"height":648,"scale":1,"time":2218},{"offsetLeft":0,"offsetTop":0,"pageLeft":0,"pageTop":2058,"width":360,"height":648,"scale":1,"time":2235},{"offsetLeft":0,"offsetTop":0,"pageLeft":0,"pageTop":2108,"width":360,"height":648,"scale":1,"time":2253},{"offsetLeft":0,"offsetTop":0,"pageLeft":0,"pageTop":2156.5,"width":360,"height":648,"scale":1,"time":2269},{"offsetLeft":0,"offsetTop":0,"pageLeft":0,"pageTop":2203.5,"width":360,"height":648,"scale":1,"time":2286},{"offsetLeft":0,"offsetTop":0,"pageLeft":0,"pageTop":2249,"width":360,"height":648,"scale":1,"time":2302},{"offsetLeft":0,"offsetTop":0,"pageLeft":0,"pageTop":2293,"width":360,"height":648,"scale":1,"time":2318},{"offsetLeft":0,"offsetTop":0,"pageLeft":0,"pageTop":2335,"width":360,"height":648,"scale":1,"time":2335},{"offsetLeft":0,"offsetTop":0,"pageLeft":0,"pageTop":2376,"width":360,"height":648,"scale":1,"time":2353},{"offsetLeft":0,"offsetTop":0,"pageLeft":0,"pageTop":2416,"width":360,"height":648,"scale":1,"time":2370},{"offsetLeft":0,"offsetTop":0,"pageLeft":0,"pageTop":2454,"width":360,"height":648,"scale":1,"time":2384},{"offsetLeft":0,"offsetTop":0,"pageLeft":0,"pageTop":2491,"width":360,"height":648,"scale":1,"time":2402},{"offsetLeft":0,"offsetTop":0,"pageLeft":0,"pageTop":2527,"width":360,"height":648,"scale":1,"time":2420},{"offsetLeft":0,"offsetTop":0,"pageLeft":0,"pageTop":2561.5,"width":360,"height":648,"scale":1,"time":2435},{"offsetLeft":0,"offsetTop":0,"pageLeft":0,"pageTop":2595,"width":360,"height":648,"scale":1,"time":2451},{"offsetLeft":0,"offsetTop":0,"pageLeft":0,"pageTop":2627,"width":360,"height":648,"scale":1,"time":2467},{"offsetLeft":0,"offsetTop":0,"pageLeft":0,"pageTop":2658,"width":360,"height":648,"scale":1,"time":2485},{"offsetLeft":0,"offsetTop":0,"pageLeft":0,"pageTop":2688.5,"width":360,"height":648,"scale":1,"time":2501},{"offsetLeft":0,"offsetTop":0,"pageLeft":0,"pageTop":2717.5,"width":360,"height":648,"scale":1,"time":2517},{"offsetLeft":0,"offsetTop":0,"pageLeft":0,"pageTop":2745.5,"width":360,"height":648,"scale":1,"time":2534},{"offsetLeft":0,"offsetTop":0,"pageLeft":0,"pageTop":2772.5,"width":360,"height":648,"scale":1,"time":2551},{"offsetLeft":0,"offsetTop":0,"pageLeft":0,"pageTop":2798.5,"width":360,"height":648,"scale":1,"time":2569},{"offsetLeft":0,"offsetTop":0,"pageLeft":0,"pageTop":2824,"width":360,"height":648,"scale":1,"time":2587},{"offsetLeft":0,"offsetTop":0,"pageLeft":0,"pageTop":2848.5,"width":360,"height":648,"scale":1,"time":2601},{"offsetLeft":0,"offsetTop":0,"pageLeft":0,"pageTop":2872,"width":360,"height":648,"scale":1,"time":2620},{"offsetLeft":0,"offsetTop":0,"pageLeft":0,"pageTop":2895,"width":360,"height":648,"scale":1,"time":2636},{"offsetLeft":0,"offsetTop":0,"pageLeft":0,"pageTop":2916.5,"width":360,"height":648,"scale":1,"time":2652},{"offsetLeft":0,"offsetTop":0,"pageLeft":0,"pageTop":2938,"width":360,"height":648,"scale":1,"time":2668},{"offsetLeft":0,"offsetTop":0,"pageLeft":0,"pageTop":2958.5,"width":360,"height":648,"scale":1,"time":2686},{"offsetLeft":0,"offsetTop":0,"pageLeft":0,"pageTop":2978,"width":360,"height":648,"scale":1,"time":2701},{"offsetLeft":0,"offsetTop":0,"pageLeft":0,"pageTop":2977.5,"width":360,"height":592,"scale":1,"time":4149},{"offsetLeft":0,"offsetTop":0,"pageLeft":0,"pageTop":2974,"width":360,"height":592,"scale":1,"time":4182},{"offsetLeft":0,"offsetTop":0,"pageLeft":0,"pageTop":2971,"width":360,"height":592,"scale":1,"time":4202},{"offsetLeft":0,"offsetTop":0,"pageLeft":0,"pageTop":2969,"width":360,"height":592,"scale":1,"time":4216},{"offsetLeft":0,"offsetTop":0,"pageLeft":0,"pageTop":2967.5,"width":360,"height":592,"scale":1,"time":4232},{"offsetLeft":0,"offsetTop":0,"pageLeft":0,"pageTop":2966.5,"width":360,"height":592,"scale":1,"time":4265},{"offsetLeft":0,"offsetTop":0,"pageLeft":0,"pageTop":2951.5,"width":360,"height":544,"scale":1,"time":4604},{"offsetLeft":0,"offsetTop":0,"pageLeft":0,"pageTop":2935,"width":360,"height":544,"scale":1,"time":4617},{"offsetLeft":0,"offsetTop":0,"pageLeft":0,"pageTop":2922.5,"width":360,"height":544,"scale":1,"time":4633},{"offsetLeft":0,"offsetTop":0,"pageLeft":0,"pageTop":2912.5,"width":360,"height":544,"scale":1,"time":4651},{"offsetLeft":0,"offsetTop":0,"pageLeft":0,"pageTop":2904,"width":360,"height":544,"scale":1,"time":4665},{"offsetLeft":0,"offsetTop":0,"pageLeft":0,"pageTop":2897.5,"width":360,"height":544,"scale":1,"time":4684},{"offsetLeft":0,"offsetTop":0,"pageLeft":0,"pageTop":2893,"width":360,"height":544,"scale":1,"time":4701},{"offsetLeft":0,"offsetTop":0,"pageLeft":0,"pageTop":2889,"width":360,"height":544,"scale":1,"time":4718},{"offsetLeft":0,"offsetTop":0,"pageLeft":0,"pageTop":2886.5,"width":360,"height":544,"scale":1,"time":4733},{"offsetLeft":0,"offsetTop":0,"pageLeft":0,"pageTop":2885.5,"width":360,"height":544,"scale":1,"time":4750},{"offsetLeft":0,"offsetTop":0,"pageLeft":0,"pageTop":2884.5,"width":360,"height":544,"scale":1,"time":4783},{"offsetLeft":0,"offsetTop":0,"pageLeft":0,"pageTop":2883,"width":360,"height":544,"scale":1,"time":4817},{"offsetLeft":0,"offsetTop":0,"pageLeft":0,"pageTop":2882,"width":360,"height":544,"scale":1,"time":4848},{"offsetLeft":0,"offsetTop":0,"pageLeft":0,"pageTop":2881.5,"width":360,"height":544,"scale":1,"time":4867},{"offsetLeft":0,"offsetTop":0,"pageLeft":0,"pageTop":2881,"width":360,"height":544,"scale":1,"time":4883},{"offsetLeft":0,"offsetTop":0,"pageLeft":0,"pageTop":2882,"width":360,"height":544,"scale":1,"time":4965},{"offsetLeft":0,"offsetTop":0,"pageLeft":0,"pageTop":2904.5,"width":360,"height":600,"scale":1,"time":9050},{"offsetLeft":0,"offsetTop":0,"pageLeft":0,"pageTop":2933.5,"width":360,"height":600,"scale":1,"time":9065},{"offsetLeft":0,"offsetTop":0,"pageLeft":0,"pageTop":2968,"width":360,"height":600,"scale":1,"time":9083},{"offsetLeft":0,"offsetTop":0,"pageLeft":0,"pageTop":3005,"width":360,"height":600,"scale":1,"time":9101},{"offsetLeft":0,"offsetTop":0,"pageLeft":0,"pageTop":3044.5,"width":360,"height":600,"scale":1,"time":9118},{"offsetLeft":0,"offsetTop":0,"pageLeft":0,"pageTop":3096.5,"width":360,"height":600,"scale":1,"time":9134},{"offsetLeft":0,"offsetTop":0,"pageLeft":0,"pageTop":3103.5,"width":360,"height":600,"scale":1,"time":9152},{"offsetLeft":0,"offsetTop":0,"pageLeft":0,"pageTop":3147.5,"width":360,"height":600,"scale":1,"time":9168},{"offsetLeft":0,"offsetTop":0,"pageLeft":0,"pageTop":3191,"width":360,"height":600,"scale":1,"time":9184},{"offsetLeft":0,"offsetTop":0,"pageLeft":0,"pageTop":3234,"width":360,"height":600,"scale":1,"time":9203},{"offsetLeft":0,"offsetTop":0,"pageLeft":0,"pageTop":3276,"width":360,"height":600,"scale":1,"time":9217},{"offsetLeft":0,"offsetTop":0,"pageLeft":0,"pageTop":3316.5,"width":360,"height":600,"scale":1,"time":9233},{"offsetLeft":0,"offsetTop":0,"pageLeft":0,"pageTop":3356,"width":360,"height":600,"scale":1,"time":9250},{"offsetLeft":0,"offsetTop":0,"pageLeft":0,"pageTop":3394,"width":360,"height":600,"scale":1,"time":9267},{"offsetLeft":0,"offsetTop":0,"pageLeft":0,"pageTop":3431,"width":360,"height":600,"scale":1,"time":9283},{"offsetLeft":0,"offsetTop":0,"pageLeft":0,"pageTop":3466.5,"width":360,"height":600,"scale":1,"time":9300},{"offsetLeft":0,"offsetTop":0,"pageLeft":0,"pageTop":3500,"width":360,"height":600,"scale":1,"time":9318},{"offsetLeft":0,"offsetTop":0,"pageLeft":0,"pageTop":3532.5,"width":360,"height":600,"scale":1,"time":9334},{"offsetLeft":0,"offsetTop":0,"pageLeft":0,"pageTop":3563.5,"width":360,"height":600,"scale":1,"time":9351},{"offsetLeft":0,"offsetTop":0,"pageLeft":0,"pageTop":3593.5,"width":360,"height":600,"scale":1,"time":9367},{"offsetLeft":0,"offsetTop":0,"pageLeft":0,"pageTop":3621.5,"width":360,"height":600,"scale":1,"time":9385},{"offsetLeft":0,"offsetTop":0,"pageLeft":0,"pageTop":3648.5,"width":360,"height":600,"scale":1,"time":9400},{"offsetLeft":0,"offsetTop":0,"pageLeft":0,"pageTop":3674.5,"width":360,"height":600,"scale":1,"time":9417},{"offsetLeft":0,"offsetTop":0,"pageLeft":0,"pageTop":3699,"width":360,"height":600,"scale":1,"time":9433},{"offsetLeft":0,"offsetTop":0,"pageLeft":0,"pageTop":3722.5,"width":360,"height":600,"scale":1,"time":9451},{"offsetLeft":0,"offsetTop":0,"pageLeft":0,"pageTop":3744.5,"width":360,"height":600,"scale":1,"time":9467},{"offsetLeft":0,"offsetTop":0,"pageLeft":0,"pageTop":3766,"width":360,"height":600,"scale":1,"time":9483},{"offsetLeft":0,"offsetTop":0,"pageLeft":0,"pageTop":3786,"width":360,"height":600,"scale":1,"time":9501}],"filename":"17_scroll"}