{"session_id":"1649877252497","state":"screen2","original_query":"?version=v3","user_agent":"Mozilla/5.0 (Linux; Android 9; P10) AppleWebKit/537.36 (KHTML, like Gecko) Chrome/100.0.4896.79 Safari/537.36","platform":"Linux armv8l","task_idx":"1","task_id":"practice2","style_id":"colborders","table_idx":"15","scroll_log":[{"offsetLeft":0,"offsetTop":0,"pageLeft":0,"pageTop":216,"width":1138.6666259765625,"height":640,"scale":1,"time":6},{"offsetLeft":0,"offsetTop":0,"pageLeft":0,"pageTop":167.11111450195312,"width":1138.6666259765625,"height":544,"scale":1,"time":1656},{"offsetLeft":0,"offsetTop":0,"pageLeft":0,"pageTop":143.11111450195312,"width":1138.6666259765625,"height":544,"scale":1,"time":1675},{"offsetLeft":0,"offsetTop":0,"pageLeft":0,"pageTop":104,"width":1138.6666259765625,"height":544,"scale":1,"time":1692},{"offsetLeft":0,"offsetTop":0,"pageLeft":0,"pageTop":65.77777862548828,"width":1138.6666259765625,"height":544,"scale":1,"time":1711},{"offsetLeft":0,"offsetTop":0,"pageLeft":0,"pageTop":28.44444465637207,"width":1138.6666259765625,"height":544,"scale":1,"time":1730},{"offsetLeft":0,"offsetTop":0,"pageLeft":0,"pageTop":0,"width":1138.6666259765625,"height":544,"scale":1,"time":1749},{"offsetLeft":0,"offsetTop":0,"pageLeft":0,"pageTop":12.44444465637207,"width":1138.6666259765625,"height":640,"scale":1,"time":7485},{"offsetLeft":0,"offsetTop":0,"pageLeft":0,"pageTop":47.11111068725586,"width":1138.6666259765625,"height":640,"scale":1,"time":7503},{"offsetLeft":0,"offsetTop":0,"pageLeft":0,"pageTop":79.11111450195312,"width":1138.6666259765625,"height":640,"scale":1,"time":7525},{"offsetLeft":0,"offsetTop":0,"pageLeft":0,"pageTop":85.33333587646484,"width":1138.6666259765625,"height":640,"scale":1,"time":7541},{"offsetLeft":0,"offsetTop":0,"pageLeft":0,"pageTop":112,"width":1138.6666259765625,"height":640,"scale":1,"time":7559},{"offsetLeft":0,"offsetTop":0,"pageLeft":0,"pageTop":138.6666717529297,"width":1138.6666259765625,"height":640,"scale":1,"time":7579},{"offsetLeft":0,"offsetTop":0,"pageLeft":0,"pageTop":162.6666717529297,"width":1138.6666259765625,"height":640,"scale":1,"time":7597},{"offsetLeft":0,"offsetTop":0,"pageLeft":0,"pageTop":186.6666717529297,"width":1138.6666259765625,"height":640,"scale":1,"time":7616},{"offsetLeft":0,"offsetTop":0,"pageLeft":0,"pageTop":208,"width":1138.6666259765625,"height":640,"scale":1,"time":7638},{"offsetLeft":0,"offsetTop":0,"pageLeft":0,"pageTop":216,"width":1138.6666259765625,"height":640,"scale":1,"time":7655}],"filename":"1_scroll"}